homography.py
homography-0.1.7.dist-info/LICENSE
homography-0.1.7.dist-info/METADATA
homography-0.1.7.dist-info/WHEEL
homography-0.1.7.dist-info/top_level.txt
homography-0.1.7.dist-info/RECORD
