Metadata-Version: 2.1
Name: homography
Version: 0.1.7
Summary: A library for dealing with 2d homography transformations.
Home-page: https://github.com/satellogic/homography
Author: Slava Kerner, Amit Aronovitch
Author-email: amit@satellogic.com
License: GPLv3
Platform: UNKNOWN
Classifier: Development Status :: 4 - Beta
Classifier: Environment :: Console
Classifier: Intended Audience :: Science/Research
Classifier: Operating System :: OS Independent
Classifier: Programming Language :: Python
Classifier: Topic :: Software Development :: Libraries :: Python Modules
Classifier: Topic :: Utilities
Requires-Dist: numpy
Requires-Dist: affine
Provides-Extra: full
Requires-Dist: Shapely ; extra == 'full'
Requires-Dist: opencv-contrib-python ; extra == 'full'
